c5/__init__.py
c5/audio.py
c5/config.py
c5/config_transform.py
c5/corpus/__init__.py
c5/corpus/collect_all_data.py
c5/data.py
c5/derived/__init__.py
c5/derived/orientation.py
c5/derived/space.py
c5/derived/speech.py
c5/derived/turntaking.py
c5/derived/visibility.py
c5/dl/__init__.py
c5/dl/sampling.py
c5/dl/tsn.py
c5/elan/__init__.py
c5/elan/reader.py
c5/elan/writer.py
c5/feedback.py
c5/output.py
c5/raw/__init__.py
c5/raw/artkp.py
c5/raw/brix.py
c5/raw/kinect.py
c5/sensors.py
c5/tools/__init__.py
c5/tools/dataviewer.py
c5/tools/helper.py
c5/tools/notebook.py
c5/tools/preprocessors.py
c5/tools/sync/__init__.py
c5/tools/sync/control/__init__.py
c5/tools/sync/control/configuration.back
c5/tools/sync/control/configuration.py
c5/tools/sync/control/dataanalysis.py
c5/tools/sync/control/itemcontrol.py
c5/tools/sync/control/videotools.py
c5/tools/sync/control/xmlwrapper.py
c5/tools/sync/data/c5.xml
c5/tools/sync/gui/EventChooser.ui
c5/tools/sync/gui/LayoutEditor.ui
c5/tools/sync/gui/VideoWidget.ui
c5/tools/sync/gui/__init__.py
c5/tools/sync/gui/cvtools.py
c5/tools/sync/gui/cvvideowidget.py
c5/tools/sync/gui/eventChooserUi.py
c5/tools/sync/gui/layoutEditorUi.py
c5/tools/sync/gui/layout_dialog.py
c5/tools/sync/gui/layout_preview.py
c5/tools/sync/gui/mainView.ui
c5/tools/sync/gui/mainViewUi.py
c5/tools/sync/gui/main_view.py
c5/tools/sync/gui/qtpromotion.py
c5/tools/sync/gui/videoWidgetUi.py
c5/tools/sync/gui/videodialog.ui
c5/tools/sync/gui/videodialogUi.py
c5/tools/sync/img/error.png
c5/tools/sync/img/okay.png
c5/tools/sync/img/unknown.png
c5/tools/sync/img/warning.png
c5/tools/sync/model/__init__.py
c5/tools/sync/model/itemmodel.py
c5/tools/sync/startup.py
c5/tools/sync/tools/__init__.py
c5/tools/sync/tools/audiocontainer.py
c5/tools/sync/tools/layoutcontainer.py
c5/tools/sync/tools/moviecontainer.py
c5/tools/twistedviewer.py
c5/video.py
c5/viewer/css/app.60c52515.css
c5/viewer/css/chunk-vendors.8b220ae0.css
c5/viewer/favicon.ico
c5/viewer/index.html
c5py-1.0.1.dist-info/entry_points.txt
c5py-1.0.1.dist-info/WHEEL
c5py-1.0.1.dist-info/METADATA
c5py-1.0.1.dist-info/RECORD
